{
  "about-quote-bg.jpg": "about-quote-bg.webp",
  "article-agentic-ai.jpg": "article-agentic-ai.webp",
  "article-ai-agent-mgmt.jpg": "article-ai-agent-mgmt.webp",
  "article-ai-bootcamp.jpg": "article-ai-bootcamp.webp",
  "article-ai-maturity.jpg": "article-ai-maturity.webp",
  "article-ai-tool-selection.jpg": "article-ai-tool-selection.webp",
  "article-ai-trends-2026.jpg": "article-ai-trends-2026.webp",
  "article-cover.jpg": "article-cover.webp",
  "article-gov-subsidy.jpg": "article-gov-subsidy.webp",
  "article-hr-ai-course.jpg": "article-hr-ai-course.webp",
  "article-hr-five-layers.jpg": "article-hr-five-layers.webp",
  "article-manufacturing-ai.jpg": "article-manufacturing-ai.webp",
  "article-service-chatbot.jpg": "article-service-chatbot.webp",
  "article-sme-esg.jpg": "article-sme-esg.webp",
  "article-strategy-subtraction.jpg": "article-strategy-subtraction.webp",
  "article-team-innovation.jpg": "article-team-innovation.webp",
  "cj-photo.jpg": "cj-photo.webp",
  "cj-portrait-full.jpg": "cj-portrait-full.webp",
  "cj-portrait.jpg": "cj-portrait.webp",
  "cta-bg.jpg": "cta-bg.webp",
  "hero-bg.jpg": "hero-bg.webp",
  "og-image-ai.jpg": "og-image-ai.webp",
  "og-image.jpg": "og-image.webp",
  "services-bg.jpg": "services-bg.webp",
  "xiaoha-avatar.jpg": "xiaoha-avatar.webp",
  "xiaoha-portrait.jpg": "xiaoha-portrait.webp"
}